synergy/__init__.py
synergy/exceptions.py
synergy/py.typed
synergy/version.py
synergy/combination/__init__.py
synergy/combination/bliss.py
synergy/combination/braid.py
synergy/combination/combination_index.py
synergy/combination/hsa.py
synergy/combination/loewe.py
synergy/combination/musyc.py
synergy/combination/schindler.py
synergy/combination/synergy_model_2d.py
synergy/combination/zero_interaction_potency.py
synergy/combination/zimmer.py
synergy/combination/jacobians/__init__.py
synergy/combination/jacobians/musyc_jacobian.py
synergy/datasets/__init__.py
synergy/datasets/data/__init__.py
synergy/higher/__init__.py
synergy/higher/bliss.py
synergy/higher/combination_index.py
synergy/higher/hsa.py
synergy/higher/loewe.py
synergy/higher/musyc.py
synergy/higher/schindler.py
synergy/higher/synergy_model_Nd.py
synergy/single/__init__.py
synergy/single/dose_response_model_1d.py
synergy/single/hill.py
synergy/single/log_linear.py
synergy/testing_utils/__init__.py
synergy/testing_utils/assertions.py
synergy/testing_utils/synthetic_data_generators.py
synergy/testing_utils/test_data_loader.py
synergy/utils/__init__.py
synergy/utils/data_exchange.py
synergy/utils/dose_utils.py
synergy/utils/model_mixins.py
synergy/utils/plots.py
synergy-1.0.0.dist-info/LICENSE
synergy-1.0.0.dist-info/METADATA
synergy-1.0.0.dist-info/WHEEL
synergy-1.0.0.dist-info/top_level.txt
synergy-1.0.0.dist-info/RECORD
