Metadata-Version: 2.1
Name: synergy
Version: 1.0.0
Author-email: "David J. Wooten" <dw@wootenlab.com>
License: GNU GENERAL PUBLIC LICENSE
Project-URL: Homepage, https://github.com/djwooten/synergy
Project-URL: Repository, https://github.com/djwooten/synergy
Project-URL: Changelog, https://github.com/djwooten/synergy/blob/main/CHANGELOG.md
Project-URL: Documentation, https://synergy.readthedocs.io/
Classifier: Development Status :: 4 - Beta
Classifier: Intended Audience :: Science/Research
Classifier: Intended Audience :: Education
Classifier: License :: OSI Approved :: GNU General Public License v3 or later (GPLv3+)
Classifier: Natural Language :: English
Classifier: Programming Language :: Python :: 3
Classifier: Operating System :: OS Independent
Classifier: Topic :: Scientific/Engineering :: Bio-Informatics
Classifier: Topic :: Scientific/Engineering :: Medical Science Apps.
Requires-Python: >=3.6
License-File: LICENSE
Requires-Dist: scipy>=0.18.0
Requires-Dist: numpy>=1.13.0
Provides-Extra: dev
Requires-Dist: ruff; extra == "dev"
Requires-Dist: mypy<1.5,>=1.0; extra == "dev"
Requires-Dist: black<24.0,>=23.0; extra == "dev"
Requires-Dist: isort<5.13,>=5.12; extra == "dev"
Requires-Dist: pytest; extra == "dev"
Requires-Dist: pytest-sphinx; extra == "dev"
Requires-Dist: pytest-cov; extra == "dev"
Requires-Dist: twine>=1.11.0; extra == "dev"
Requires-Dist: build; extra == "dev"
Requires-Dist: setuptools; extra == "dev"
Requires-Dist: wheel; extra == "dev"
Requires-Dist: Sphinx<7.1.0,>=4.3.0; extra == "dev"
Requires-Dist: sphinx-rtd-theme; extra == "dev"
Requires-Dist: myst-parser<2.1,>=1.0; extra == "dev"
Requires-Dist: sphinx-copybutton==0.5.2; extra == "dev"
Requires-Dist: sphinx-autobuild==2021.3.14; extra == "dev"
Requires-Dist: sphinx-autodoc-typehints==1.23.3; extra == "dev"
Requires-Dist: packaging; extra == "dev"
Requires-Dist: ipython; extra == "dev"
Requires-Dist: notebook; extra == "dev"
Requires-Dist: nbsphinx; extra == "dev"
Requires-Dist: hypothesis; extra == "dev"
Provides-Extra: plot
